pushbullet_cli/__init__.py
pushbullet_cli/__version__.py
pushbullet_cli/app.py
pushbullet_cli-1.2.2.dist-info/LICENSE.txt
pushbullet_cli-1.2.2.dist-info/METADATA
pushbullet_cli-1.2.2.dist-info/WHEEL
pushbullet_cli-1.2.2.dist-info/entry_points.txt
pushbullet_cli-1.2.2.dist-info/top_level.txt
pushbullet_cli-1.2.2.dist-info/RECORD
