Metadata-Version: 2.1
Name: pushbullet-cli
Version: 1.2.2
Summary: Command line tool for controlling PushBullet
Home-page: https://github.com/GustavoKatel/pushbullet-cli
Author: Gustavo Sampaio
Author-email: gbritosampaio@gmail.com
License: UNKNOWN
Platform: UNKNOWN
License-File: LICENSE.txt
Requires-Dist: click (~=8.1)
Requires-Dist: pushbullet.py (~=0.12.0)
Requires-Dist: keyring (~=23.5.0)
Requires-Dist: keyrings.alt (~=4.1.0)
